{
  "main": {
    "id": "3a5608a61e6dc5eb",
    "type": "split",
    "children": [
      {
        "id": "88ea8cbfc1eb3935",
        "type": "tabs",
        "children": [
          {
            "id": "5a8b2c5d8b6b5152",
            "type": "leaf",
            "state": {
              "type": "markdown",
              "state": {
                "file": "Notes/DataStack/Modele do szeregów stacjonarnych (AR i MA).md",
                "mode": "source",
                "source": false
              },
              "icon": "lucide-file",
              "title": "Modele do szeregów stacjonarnych (AR i MA)"
            }
          },
          {
            "id": "cb82e8ef1b563a57",
            "type": "leaf",
            "state": {
              "type": "markdown",
              "state": {
                "file": "Notes/DataStack/Modele szeregów stacjonarnych (ARMA, ARIMAX, SARIMAX).md",
                "mode": "source",
                "source": false
              },
              "icon": "lucide-file",
              "title": "Modele szeregów stacjonarnych (ARMA, ARIMAX, SARIMAX)"
            }
          }
        ]
      }
    ],
    "direction": "vertical"
  },
  "left": {
    "id": "c8329f143e1f016b",
    "type": "split",
    "children": [
      {
        "id": "2ac57018aeb73472",
        "type": "tabs",
        "children": [
          {
            "id": "5d97a957da2bdd5d",
            "type": "leaf",
            "state": {
              "type": "file-explorer",
              "state": {
                "sortOrder": "alphabetical",
                "autoReveal": false
              },
              "icon": "lucide-folder-closed",
              "title": "Files"
            }
          },
          {
            "id": "b1e644aaa397385a",
            "type": "leaf",
            "state": {
              "type": "search",
              "state": {
                "query": "",
                "matchingCase": true,
                "explainSearch": false,
                "collapseAll": false,
                "extraContext": false,
                "sortOrder": "alphabetical"
              },
              "icon": "lucide-search",
              "title": "Search"
            }
          },
          {
            "id": "fcf71de37c0196d0",
            "type": "leaf",
            "state": {
              "type": "bookmarks",
              "state": {},
              "icon": "lucide-bookmark",
              "title": "Bookmarks"
            }
          }
        ]
      }
    ],
    "direction": "horizontal",
    "width": 405.5
  },
  "right": {
    "id": "905d5a3b995a9739",
    "type": "split",
    "children": [
      {
        "id": "8f6ade9aa4c809a4",
        "type": "tabs",
        "children": [
          {
            "id": "18c759ef674643cf",
            "type": "leaf",
            "state": {
              "type": "backlink",
              "state": {
                "file": "Template/Default Template.md",
                "collapseAll": false,
                "extraContext": false,
                "sortOrder": "alphabetical",
                "showSearch": false,
                "searchQuery": "",
                "backlinkCollapsed": false,
                "unlinkedCollapsed": true
              },
              "icon": "links-coming-in",
              "title": "Backlinks for Default Template"
            }
          },
          {
            "id": "d77c2f9fb4356de2",
            "type": "leaf",
            "state": {
              "type": "outgoing-link",
              "state": {
                "file": "Template/Default Template.md",
                "linksCollapsed": false,
                "unlinkedCollapsed": true
              },
              "icon": "links-going-out",
              "title": "Outgoing links from Default Template"
            }
          },
          {
            "id": "065a568ea2428dee",
            "type": "leaf",
            "state": {
              "type": "tag",
              "state": {
                "sortOrder": "frequency",
                "useHierarchy": true
              },
              "icon": "lucide-tags",
              "title": "Tags"
            }
          },
          {
            "id": "50f481ca94133d5d",
            "type": "leaf",
            "state": {
              "type": "outline",
              "state": {
                "file": "Notes/Running scripts.md",
                "followCursor": false,
                "showSearch": false,
                "searchQuery": ""
              },
              "icon": "lucide-list",
              "title": "Outline of Running scripts"
            }
          },
          {
            "id": "ae06123304d97c5e",
            "type": "leaf",
            "state": {
              "type": "git-view",
              "state": {},
              "icon": "git-pull-request",
              "title": "Source Control"
            }
          }
        ],
        "currentTab": 4
      }
    ],
    "direction": "horizontal",
    "width": 300
  },
  "left-ribbon": {
    "hiddenItems": {
      "switcher:Open quick switcher": false,
      "graph:Open graph view": false,
      "canvas:Create new canvas": false,
      "daily-notes:Open today's daily note": false,
      "templates:Insert template": false,
      "command-palette:Open command palette": false,
      "obsidian-git:Open Git source control": false
    }
  },
  "active": "5a8b2c5d8b6b5152",
  "lastOpenFiles": [
    "Notes/DataStack/Modele szeregów stacjonarnych (ARMA, ARIMAX, SARIMAX).md",
    "Notes/DataStack/Modele do szeregów stacjonarnych (AR i MA).md",
    "Notes/UV.md",
    "Notes/Dodawanie paczek.md",
    "Notes/DataStack/Pandas początek i wczytywanie danych.md",
    "Notes/DataStack/Pandas podstawowe operacje na danych.md",
    "Notes/DataStack/Rysunek maltplotlib.md",
    "Notes/DataStack/DataFrame.md",
    "Notes/DataStack/Struktura projektu Data Science.md",
    "Notes/Docker/Docker.md",
    "Notes/Pytest folder/Pytest Fixture.md",
    "Notes/Pytest folder/Fixtures.md",
    "Notes/Container.md",
    "Notes/Pytest folder",
    "Notes/DataStack",
    "Notes/Docker",
    "Notes/Pytest folder/Pytest Wtyczki.md",
    "Notes/Series.md",
    "Notes/Pytest folder/Pytest.md",
    "Notes/Pytest folder/Pytest  i testy jednostkowe.md",
    "Notes/Pytest folder/Pytest CLI.md",
    "Notes/Pytest folder/TestCase.md",
    "Notes/Pytest folder/Pytest Coverage.md",
    "Notes/String.md",
    "Notes/Sized.md",
    "Notes/Protocols.md",
    "Notes/Iterable,Iterator.md",
    "Notes/Hashable.md",
    "Pasted image 20250211223032.png",
    "Pasted image 20250211222957.png",
    "CV/Socials.md",
    "CV",
    "Untitled.canvas",
    "Protocols Python",
    "Notes",
    "Template"
  ]
}